LICENSE.txt
MANIFEST.in
README.md
setup.py
django_angular_url/__init__.py
django_angular_url/models.py
django_angular_url.egg-info/PKG-INFO
django_angular_url.egg-info/SOURCES.txt
django_angular_url.egg-info/dependency_links.txt
django_angular_url.egg-info/requires.txt
django_angular_url.egg-info/top_level.txt
django_angular_url/core/__init__.py
django_angular_url/core/urlresolvers.py
django_angular_url/static/django_angular_url/js/django-angular-url.js
django_angular_url/static/django_angular_url/js/django-angular-url.min.js
django_angular_url/static/django_angular_url/js/django-angular.js
django_angular_url/static/django_angular_url/js/django-angular.min.js
django_angular_url/templatetags/__init__.py
django_angular_url/templatetags/django_angular_url_tags.py